git_aggregator/__init__.py
git_aggregator/_compat.py
git_aggregator/config.py
git_aggregator/exception.py
git_aggregator/log.py
git_aggregator/main.py
git_aggregator/repo.py
git_aggregator/utils.py
git_aggregator-4.1.dist-info/licenses/LICENSE
git_aggregator-4.1.dist-info/METADATA
git_aggregator-4.1.dist-info/WHEEL
git_aggregator-4.1.dist-info/entry_points.txt
git_aggregator-4.1.dist-info/top_level.txt
git_aggregator-4.1.dist-info/RECORD
