Metadata-Version: 2.4
Name: git_aggregator
Version: 4.1
Summary: A program to aggregate git branches from different remotes into a consolidated one
Home-page: http://github.com/acsone/git-aggregator
Author: ACSONE SA/NV
Author-email: info@acsone.eu
License: AGPLv3+
Classifier: Development Status :: 5 - Production/Stable
Classifier: Intended Audience :: Developers
Classifier: License :: OSI Approved :: GNU Affero General Public License v3 or later (AGPLv3+)
Classifier: Operating System :: POSIX
Classifier: Programming Language :: Python :: 3
Classifier: Programming Language :: Python :: 3.9
Classifier: Programming Language :: Python :: 3.10
Classifier: Programming Language :: Python :: 3.11
Classifier: Programming Language :: Python :: 3.12
Classifier: Programming Language :: Python :: 3.13
Classifier: Topic :: Utilities
Classifier: Topic :: System :: Shells
Requires-Python: >=3.7
License-File: LICENSE
Requires-Dist: PyYAML>=5
Requires-Dist: argcomplete
Requires-Dist: colorama
Requires-Dist: requests
Dynamic: author
Dynamic: author-email
Dynamic: classifier
Dynamic: description
Dynamic: home-page
Dynamic: license
Dynamic: license-file
Dynamic: requires-dist
Dynamic: requires-python
Dynamic: summary
